[{"name":"EEF1A1","score":0.0008419,"ge":13.8927424,"geLevel":"NORMAL","mtb":false},{"name":"ACTB","score":0.0006146,"ge":13.3831427,"geLevel":"NORMAL","mtb":false},{"name":"HUWE1","score":0.0008123,"ge":13.0958051,"geLevel":"NORMAL","mtb":false},{"name":"CFL1","score":0.0007771,"ge":12.5873964,"geLevel":"NORMAL","mtb":false},{"name":"TMSB10","score":0.0010354,"ge":13.5245656,"geLevel":"HIGH","mtb":false},{"name":"COL1A2","score":0.001027,"ge":13.752067,"geLevel":"HIGH","mtb":false},{"name":"ANXA2","score":0.0008567,"ge":12.6638964,"geLevel":"HIGH","mtb":false},{"name":"FN1","score":0.0008668,"ge":12.7135966,"geLevel":"NORMAL","mtb":false},{"name":"CD24","score":0.0007186,"ge":12.1579386,"geLevel":"NORMAL","mtb":false},{"name":"COL3A1","score":0.0010882,"ge":13.3036648,"geLevel":"HIGH","mtb":false},{"name":"TMSB4X","score":0.0007732,"ge":12.2586169,"geLevel":"HIGH","mtb":false},{"name":"ALDOA","score":0.0006189,"ge":11.2185673,"geLevel":"NORMAL","mtb":false},{"name":"COL1A1","score":0.0009997,"ge":13.6150731,"geLevel":"HIGH","mtb":false},{"name":"HSP90AB1","score":0.0005387,"ge":11.1078529,"geLevel":"LOW","mtb":false},{"name":"LDHA","score":0.000699,"ge":11.8849775,"geLevel":"HIGH","mtb":false},{"name":"LAMP1","score":0.0006777,"ge":11.5757006,"geLevel":"NORMAL","mtb":false},{"name":"LGALS1","score":0.0009504,"ge":11.8652907,"geLevel":"NORMAL","mtb":false},{"name":"CD63","score":0.0006225,"ge":11.3081731,"geLevel":"NORMAL","mtb":false},{"name":"KRT18","score":0.0004674,"ge":10.2629091,"geLevel":"LOW","mtb":false},{"name":"YWHAB","score":0.0005878,"ge":11.25083,"geLevel":"NORMAL","mtb":false},{"name":"SPARC","score":0.0007545,"ge":12.26519,"geLevel":"HIGH","mtb":false},{"name":"KRT19","score":0.0008553,"ge":11.5934353,"geLevel":"NORMAL","mtb":false},{"name":"GLUL","score":0.0004879,"ge":10.8750236,"geLevel":"NORMAL","mtb":false},{"name":"COL6A3","score":0.0006714,"ge":11.782898,"geLevel":"HIGH","mtb":false},{"name":"S100A10","score":0.0005028,"ge":10.829008,"geLevel":"NORMAL","mtb":false},{"name":"RAB1A","score":0.0005743,"ge":11.8334153,"geLevel":"HIGH","mtb":false},{"name":"ITGB1","score":0.0007051,"ge":11.8205813,"geLevel":"HIGH","mtb":false},{"name":"LGALS3","score":0.0004792,"ge":10.7450502,"geLevel":"NORMAL","mtb":false},{"name":"ACTA2","score":0.0008288,"ge":11.7952547,"geLevel":"HIGH","mtb":false},{"name":"S100A11","score":0.0004693,"ge":10.7152506,"geLevel":"NORMAL","mtb":false},{"name":"IGFBP7","score":0.000609,"ge":11.1707071,"geLevel":"NORMAL","mtb":false},{"name":"TAGLN2","score":0.0006108,"ge":10.616271,"geLevel":"NORMAL","mtb":false},{"name":"PGK1","score":0.0006095,"ge":11.6472489,"geLevel":"HIGH","mtb":false},{"name":"MORF4L1","score":0.0006399,"ge":11.4412516,"geLevel":"HIGH","mtb":false},{"name":"TUBA1A","score":0.0005523,"ge":11.0486102,"geLevel":"HIGH","mtb":false},{"name":"TPM1","score":0.0005911,"ge":10.520926,"geLevel":"NORMAL","mtb":false},{"name":"SNX3","score":0.0004789,"ge":10.6114361,"geLevel":"NORMAL","mtb":false},{"name":"TPI1","score":0.0004748,"ge":10.6138763,"geLevel":"NORMAL","mtb":false},{"name":"LAPTM4B","score":0.0007331,"ge":11.9631337,"geLevel":"HIGH","mtb":false},{"name":"COL6A1","score":0.000489,"ge":10.4224838,"geLevel":"NORMAL","mtb":false},{"name":"VCAN","score":0.0006358,"ge":11.0036742,"geLevel":"NORMAL","mtb":false},{"name":"CD99","score":0.0005628,"ge":11.5993156,"geLevel":"HIGH","mtb":false},{"name":"LDHB","score":0.0005943,"ge":11.552216,"geLevel":"HIGH","mtb":false},{"name":"CD164","score":0.0005084,"ge":10.1803279,"geLevel":"NORMAL","mtb":false},{"name":"NDUFB1","score":0.0006869,"ge":11.3476954,"geLevel":"HIGH","mtb":false},{"name":"ARHGDIB","score":0.0005413,"ge":10.3810039,"geLevel":"NORMAL","mtb":false},{"name":"TPD52","score":0.0005924,"ge":11.0410234,"geLevel":"HIGH","mtb":false},{"name":"SAP18","score":0.0004777,"ge":10.1939272,"geLevel":"NORMAL","mtb":false},{"name":"TAGLN","score":0.0004806,"ge":11.1577424,"geLevel":"HIGH","mtb":false},{"name":"SOX4","score":0.0006417,"ge":10.9855309,"geLevel":"HIGH","mtb":false},{"name":"SDCBP","score":0.0007165,"ge":10.6089914,"geLevel":"HIGH","mtb":false},{"name":"LASP1","score":0.0004605,"ge":9.6269007,"geLevel":"NORMAL","mtb":false},{"name":"SPARCL1","score":0.0005816,"ge":9.9043578,"geLevel":"NORMAL","mtb":false},{"name":"YWHAE","score":0.0004867,"ge":9.7908609,"geLevel":"NORMAL","mtb":false},{"name":"COL6A2","score":0.0004809,"ge":10.4741078,"geLevel":"NORMAL","mtb":false},{"name":"COL4A2","score":0.0004986,"ge":10.6209987,"geLevel":"HIGH","mtb":false},{"name":"RBBP7","score":0.0005661,"ge":10.5121062,"geLevel":"HIGH","mtb":false},{"name":"CYFIP1","score":0.0005602,"ge":10.0109393,"geLevel":"NORMAL","mtb":false},{"name":"ACTN1","score":0.0005324,"ge":10.2483349,"geLevel":"HIGH","mtb":false},{"name":"SEC13","score":0.0004638,"ge":10.1079607,"geLevel":"HIGH","mtb":false},{"name":"EPCAM","score":0.0005882,"ge":11.3728703,"geLevel":"HIGH","mtb":false},{"name":"COL4A1","score":0.0005096,"ge":10.8078499,"geLevel":"HIGH","mtb":false},{"name":"THBS2","score":0.0004997,"ge":10.6838343,"geLevel":"HIGH","mtb":false},{"name":"TMEM147","score":0.0004692,"ge":9.9822934,"geLevel":"HIGH","mtb":false},{"name":"SERPINF1","score":0.0005073,"ge":10.4560372,"geLevel":"HIGH","mtb":false},{"name":"YME1L1","score":0.0009731,"ge":9.9449181,"geLevel":"HIGH","mtb":false},{"name":"COL5A2","score":0.0005295,"ge":11.187886,"geLevel":"HIGH","mtb":false},{"name":"MTHFD2","score":0.0007008,"ge":10.3323845,"geLevel":"HIGH","mtb":false},{"name":"SULF1","score":0.0005546,"ge":10.1894427,"geLevel":"HIGH","mtb":false},{"name":"ITGAV","score":0.0005109,"ge":10.1954884,"geLevel":"HIGH","mtb":false},{"name":"SHMT2","score":0.0004734,"ge":9.2714651,"geLevel":"NORMAL","mtb":false},{"name":"RANBP9","score":0.0005157,"ge":10.0059528,"geLevel":"HIGH","mtb":false},{"name":"KRT7","score":0.0004712,"ge":10.3047519,"geLevel":"HIGH","mtb":false},{"name":"COPS5","score":0.0004737,"ge":10.0859267,"geLevel":"HIGH","mtb":false},{"name":"SRSF8","score":0.000531,"ge":8.8403788,"geLevel":"NORMAL","mtb":false},{"name":"MRPL42","score":0.0005348,"ge":9.1203949,"geLevel":"HIGH","mtb":false},{"name":"CEACAM6","score":0.0007,"ge":11.2936747,"geLevel":"HIGH","mtb":false},{"name":"SDC2","score":0.0005134,"ge":9.6074286,"geLevel":"HIGH","mtb":false},{"name":"KRT15","score":0.0005004,"ge":10.5449577,"geLevel":"HIGH","mtb":false}]